analyze_html/__init__.py
analyze_html/cli.py
analyze_html/scrap.py
analyze_html-0.1.0.dist-info/METADATA
analyze_html-0.1.0.dist-info/WHEEL
analyze_html-0.1.0.dist-info/RECORD
