Metadata-Version: 2.1
Name: analyze-html
Version: 0.1.0
Summary: 
Author: rianaditro
Author-email: rianaditro@gmail.com
Requires-Python: >=3.10,<4.0
Classifier: Programming Language :: Python :: 3
Classifier: Programming Language :: Python :: 3.10
Classifier: Programming Language :: Python :: 3.11
Classifier: Programming Language :: Python :: 3.12
Requires-Dist: beautifulsoup4 (>=4.12.3,<5.0.0)
Requires-Dist: requests (>=2.31.0,<3.0.0)
